kahmi/__init__.py
kahmi/dsl/__init__.py
kahmi/dsl/__main__.py
kahmi/dsl/ast.py
kahmi/dsl/parser.py
kahmi/dsl/py.typed
kahmi/dsl/runtime.py
kahmi/dsl/transpiler.py
kahmi/dsl/util.py
kahmi/dsl/macros/__init__.py
kahmi/dsl/macros/yaml.py
kahmi_dsl-0.1.2.dist-info/METADATA
kahmi_dsl-0.1.2.dist-info/WHEEL
kahmi_dsl-0.1.2.dist-info/entry_points.txt
kahmi_dsl-0.1.2.dist-info/top_level.txt
kahmi_dsl-0.1.2.dist-info/RECORD
