Metadata-Version: 2.1
Name: kahmi-dsl
Version: 0.1.2
Summary: Parser and transpiler for the Kahmi DSL.
Home-page: UNKNOWN
Author: Niklas Rosenstein
Author-email: rosensteinniklas@gmail.com
License: UNKNOWN
Platform: UNKNOWN
Requires-Python: >=3.6.0,<4.0.0
Requires-Dist: astor (<1.0.0,>=0.8.1)
Requires-Dist: nr.parsing.core (<2.0.0,>=1.1.0)
Requires-Dist: nr.pylang.ast (<0.1.0,>=0.0.5)
Requires-Dist: dataclasses (<1.0.0,>=0.6.0)
Requires-Dist: nr.functional (<1.0.0,>=0.1.0)
